LICENSE
MANIFEST.in
README.rst
setup.cfg
setup.py
xcovlib/__init__.py
xcovlib/client.py
xcovlib.egg-info/PKG-INFO
xcovlib.egg-info/SOURCES.txt
xcovlib.egg-info/dependency_links.txt
xcovlib.egg-info/requires.txt
xcovlib.egg-info/top_level.txt
xcovlib/api/__init__.py
xcovlib/api/base.py
xcovlib/api/bookings.py
xcovlib/api/policytypes.py
xcovlib/api/quotes.py
xcovlib/api/renewals.py
xcovlib/http/__init__.py
xcovlib/http/auth.py
xcovlib/http/base.py
xcovlib/http/exceptions.py
xcovlib/http/generic.py
xcovlib/http/http_requests.py
xcovlib/http/tests/__init__.py
xcovlib/http/tests/test_auth.py
xcovlib/http/tests/test_requests.py
xcovlib/registry/__init__.py
xcovlib/registry/registry.py
xcovlib/tests/__init__.py
xcovlib/tests/test_client.py
xcovlib/utils/__init__.py
xcovlib/utils/dates.py